netunicorn/director/infrastructure/connectors/__init__.py
netunicorn/director/infrastructure/connectors/docker_connector.py
netunicorn_connector_docker-0.1.7.dist-info/licenses/LICENSE
netunicorn_connector_docker-0.1.7.dist-info/METADATA
netunicorn_connector_docker-0.1.7.dist-info/WHEEL
netunicorn_connector_docker-0.1.7.dist-info/top_level.txt
netunicorn_connector_docker-0.1.7.dist-info/RECORD
