Metadata-Version: 2.4
Name: netunicorn-connector-docker
Version: 0.1.7
Summary: Local Docker connector for netunicorn
Author-email: Roman Beltiukov <rbeltiukov@ucsb.edu>
License: MIT
Keywords: netunicorn
Classifier: Programming Language :: Python :: 3
Requires-Python: >=3.10
License-File: LICENSE
Requires-Dist: netunicorn-base<0.5.0,>=0.4.0
Requires-Dist: docker
Requires-Dist: returns
Dynamic: license-file
